pyramid_mock_server/__init__.py
pyramid_mock_server/enhance_swagger_spec.py
pyramid_mock_server/jinja_utils.py
pyramid_mock_server/mock_loader.py
pyramid_mock_server/response_collection.py
pyramid_mock_server/swagger_util.py
pyramid_mock_server/util.py
pyramid_mock_server/view_maker.py
pyramid_mock_server-1.3.2.dist-info/LICENSE
pyramid_mock_server-1.3.2.dist-info/METADATA
pyramid_mock_server-1.3.2.dist-info/WHEEL
pyramid_mock_server-1.3.2.dist-info/entry_points.txt
pyramid_mock_server-1.3.2.dist-info/top_level.txt
pyramid_mock_server-1.3.2.dist-info/RECORD
