Metadata-Version: 2.1
Name: pyramid-mock-server
Version: 1.3.2
Summary: Create pyramid server that return mocked response from an OpenAPI spec
Home-page: https://github.com/Yelp/pyramid_mock_server
Author: Yelp, Inc.
Author-email: opensource+pyramid_mock_server@yelp.com
License: BSD 3-Clause License
Platform: UNKNOWN
Classifier: Development Status :: 5 - Production/Stable
Classifier: Intended Audience :: Developers
Classifier: Topic :: Software Development :: Libraries :: Python Modules
Classifier: License :: OSI Approved :: BSD License
Classifier: Operating System :: OS Independent
Classifier: Programming Language :: Python :: 2.7
Classifier: Programming Language :: Python :: 3.4
Classifier: Programming Language :: Python :: 3.5
Classifier: Programming Language :: Python :: 3.6
Requires-Dist: jinja2 (>=2.7)
Requires-Dist: pyramid (>=1.4)
Requires-Dist: six
Requires-Dist: venusian (>=1.0)
Provides-Extra: cli
Requires-Dist: bravado-core ; extra == 'cli'
Requires-Dist: pyramid-swagger (>=2.3.0) ; extra == 'cli'
Requires-Dist: webtest ; extra == 'cli'
Provides-Extra: pyramid-swagger
Requires-Dist: pyramid-swagger (>=2.3.0) ; extra == 'pyramid-swagger'
